bytedvrtvengine/__init__.py
bytedvrtvengine-0.0.1.dist-info/METADATA
bytedvrtvengine-0.0.1.dist-info/WHEEL
bytedvrtvengine-0.0.1.dist-info/top_level.txt
bytedvrtvengine-0.0.1.dist-info/RECORD
