Metadata-Version: 2.1
Name: bytedvrtvengine
Version: 0.0.1
Summary: A simple package named bytedvrtvengine
Home-page: https://github.com/artifact/bytedvrtvengine.git
Author: artifact
Author-email: artifact@example.com
License: UNKNOWN
Platform: UNKNOWN
Classifier: Programming Language :: Python :: 3
Classifier: License :: OSI Approved :: MIT License
Classifier: Operating System :: OS Independent
